visflow/__init__.py
visflow/__main__.py
visflow/_cli/__init__.py
visflow/_cli/args.py
visflow/_cli/commands/__init__.py
visflow/_cli/commands/gradcam.py
visflow/_cli/commands/init.py
visflow/_cli/commands/test.py
visflow/_cli/commands/train.py
visflow/context.py
visflow/data.py
visflow/exceptions.py
visflow/helpers/__init__.py
visflow/helpers/display.py
visflow/helpers/downloader.py
visflow/helpers/early_stopping.py
visflow/helpers/functional.py
visflow/helpers/gradcam.py
visflow/helpers/metrics.py
visflow/helpers/plotting.py
visflow/helpers/slotted.py
visflow/pipelines/__init__.py
visflow/pipelines/gradcam.py
visflow/pipelines/init.py
visflow/pipelines/test.py
visflow/pipelines/train.py
visflow/py.typed
visflow/resources/__init__.py
visflow/resources/config/__init__.py
visflow/resources/config/augmentation.py
visflow/resources/config/data.py
visflow/resources/config/logging.py
visflow/resources/config/lr_scheduler/__init__.py
visflow/resources/config/lr_scheduler/cosine.py
visflow/resources/config/lr_scheduler/plateau.py
visflow/resources/config/lr_scheduler/step.py
visflow/resources/config/model.py
visflow/resources/config/normalization.py
visflow/resources/config/output.py
visflow/resources/config/resize.py
visflow/resources/config/testing.py
visflow/resources/config/training.py
visflow/resources/logger/__init__.py
visflow/resources/logger/loguru.py
visflow/resources/logger/native.py
visflow/resources/logger/types.py
visflow/resources/models/__init__.py
visflow/types.py
visflow/utils/__init__.py
visflow/utils/ansi.py
visflow/utils/functional.py
visflow-1.0.5.dist-info/METADATA
visflow-1.0.5.dist-info/WHEEL
visflow-1.0.5.dist-info/entry_points.txt
visflow-1.0.5.dist-info/licenses/LICENSE
visflow-1.0.5.dist-info/RECORD
