Metadata-Version: 2.4
Name: visflow
Version: 1.0.5
Summary: A comprehensive computer vision framework for training, evaluation, and visualization with support for multiple architectures and GradCAM analysis
License: MIT
License-File: LICENSE
Keywords: computer vision,deep learning,pytorch,gradcam,machine learning,neural networks
Author: BoChen SHEN
Author-email: 6goddddddd@gmail.com
Requires-Python: >=3.11,<=3.12
Classifier: Development Status :: 4 - Beta
Classifier: Intended Audience :: Developers
Classifier: Intended Audience :: Science/Research
Classifier: License :: OSI Approved :: MIT License
Classifier: Operating System :: OS Independent
Classifier: Programming Language :: Python :: 3
Classifier: Programming Language :: Python :: 3.11
Classifier: Programming Language :: Python :: 3.12
Classifier: Topic :: Scientific/Engineering :: Artificial Intelligence
Classifier: Topic :: Software Development :: Libraries :: Python Modules
Provides-Extra: dev
Provides-Extra: test
Requires-Dist: black (>=23.0.0) ; extra == "dev"
Requires-Dist: flake8 (>=6.0.0) ; extra == "dev"
Requires-Dist: grad-cam (>=1.5.5,<2.0.0)
Requires-Dist: halo (>=0.0.31,<0.0.32)
Requires-Dist: httpx (>=0.28.1,<0.29.0)
Requires-Dist: isort (>=5.12.0) ; extra == "dev"
Requires-Dist: matplotlib (>=3.10.6,<4.0.0)
Requires-Dist: mypy (>=1.18.1,<2.0.0) ; extra == "test"
Requires-Dist: numpy (>=2.3.2,<3.0.0)
Requires-Dist: onnx (>=1.19.0,<2.0.0)
Requires-Dist: onnxruntime (>=1.22.1,<2.0.0)
Requires-Dist: psutil (>=7.0.0,<8.0.0)
Requires-Dist: pydantic (>=2.11.7,<3.0.0)
Requires-Dist: pydantic-settings (>=2.10.1,<3.0.0)
Requires-Dist: pyfiglet (>=1.0.4,<2.0.0)
Requires-Dist: pytest (>=7.0.0) ; extra == "test"
Requires-Dist: pytest-cov (>=4.0.0) ; extra == "test"
Requires-Dist: pyyaml (>=6.0.2,<7.0.0)
Requires-Dist: rich (>=14.1.0,<15.0.0)
Requires-Dist: scikit-learn (>=1.7.1,<2.0.0)
Requires-Dist: seaborn (>=0.13.2,<0.14.0)
Requires-Dist: tenacity (>=9.1.2,<10.0.0)
Requires-Dist: torch (>=2.8.0,<3.0.0)
Requires-Dist: torchvision (>=0.23.0,<0.24.0)
Requires-Dist: tqdm (>=4.67.1,<5.0.0)
Requires-Dist: types-pyyaml (>=6.0.12.20250915,<7.0.0.0) ; extra == "test"
Project-URL: Bug Tracker, https://github.com/6ixGODD/visflow/issues
Project-URL: Documentation, https://github.com/6ixGODD/visflow#readme
Project-URL: Homepage, https://github.com/6ixGODD/visflow
Project-URL: Repository, https://github.com/6ixGODD/visflow
